erdpy/__init__.py
erdpy/_version.py
erdpy/accounts.py
erdpy/accounts_repository.py
erdpy/cli.py
erdpy/cli_accounts.py
erdpy/cli_block.py
erdpy/cli_config.py
erdpy/cli_contracts.py
erdpy/cli_data.py
erdpy/cli_delegation.py
erdpy/cli_deps.py
erdpy/cli_dns.py
erdpy/cli_ledger.py
erdpy/cli_network.py
erdpy/cli_output.py
erdpy/cli_password.py
erdpy/cli_shared.py
erdpy/cli_testnet.py
erdpy/cli_transactions.py
erdpy/cli_validators.py
erdpy/cli_wallet.py
erdpy/config.py
erdpy/constants.py
erdpy/contract_verification.py
erdpy/contracts.py
erdpy/diskcache.py
erdpy/dns.py
erdpy/docker.py
erdpy/downloader.py
erdpy/errors.py
erdpy/guards.py
erdpy/interfaces.py
erdpy/myprocess.py
erdpy/scope.py
erdpy/simulation.py
erdpy/transactions.py
erdpy/utils.py
erdpy/workstation.py
erdpy/delegation/__init__.py
erdpy/delegation/staking_provider.py
erdpy/dependencies/__init__.py
erdpy/dependencies/install.py
erdpy/dependencies/modules.py
erdpy/ledger/__init__.py
erdpy/ledger/config.py
erdpy/ledger/ledger_app_handler.py
erdpy/ledger/ledger_functions.py
erdpy/projects/__init__.py
erdpy/projects/core.py
erdpy/projects/eei_activation.py
erdpy/projects/eei_checks.py
erdpy/projects/eei_registry.py
erdpy/projects/interfaces.py
erdpy/projects/project_base.py
erdpy/projects/project_clang.py
erdpy/projects/project_cpp.py
erdpy/projects/project_rust.py
erdpy/projects/project_sol.py
erdpy/projects/shared.py
erdpy/projects/templates.py
erdpy/projects/templates_config.py
erdpy/projects/templates_repository.py
erdpy/projects/report/__init__.py
erdpy/projects/report/do_report.py
erdpy/projects/report/report_creator.py
erdpy/projects/report/data/__init__.py
erdpy/projects/report/data/common.py
erdpy/projects/report/data/extracted_feature.py
erdpy/projects/report/data/folder_report.py
erdpy/projects/report/data/project_report.py
erdpy/projects/report/data/report.py
erdpy/projects/report/data/wasm_report.py
erdpy/projects/report/features/__init__.py
erdpy/projects/report/features/features.py
erdpy-4.0.0.dist-info/LICENSE
erdpy-4.0.0.dist-info/METADATA
erdpy-4.0.0.dist-info/WHEEL
erdpy-4.0.0.dist-info/entry_points.txt
erdpy-4.0.0.dist-info/top_level.txt
erdpy-4.0.0.dist-info/RECORD
