Metadata-Version: 2.1
Name: erdpy
Version: 4.0.0
Summary: MultiversX Smart Contracts Tools
Home-page: https://github.com/multiversx/mx-sdk-erdpy
Author: MultiversX
License: GPL
Keywords: MultiversX
Classifier: Programming Language :: Python :: 3.8
Classifier: Programming Language :: Python :: 3.9
Classifier: License :: OSI Approved :: GNU General Public License (GPL)
Classifier: Operating System :: POSIX :: Linux
Classifier: Intended Audience :: Developers
Classifier: Development Status :: 3 - Alpha
Requires-Python: >=3.8
License-File: LICENSE
Requires-Dist: toml (>=0.10.2)
Requires-Dist: bottle
Requires-Dist: requests
Requires-Dist: pynacl
Requires-Dist: pycryptodomex
Requires-Dist: cryptography (==36.0.2)
Requires-Dist: prettytable
Requires-Dist: ledgercomm[hid]
Requires-Dist: semver
Requires-Dist: requests-cache
Requires-Dist: mx-sdk-build-contract-rs (==4.0.0)
